OzEngine/Engine.py
OzEngine/__init__.py
Oz_Engine/OzEngine/Engine.py
Oz_Engine/OzEngine/__init__.py
Oz_Engine-1.7.2.dist-info/METADATA
Oz_Engine-1.7.2.dist-info/WHEEL
Oz_Engine-1.7.2.dist-info/top_level.txt
Oz_Engine-1.7.2.dist-info/zip-safe
Oz_Engine-1.7.2.dist-info/RECORD
