Metadata-Version: 2.1
Name: Oz-Engine
Version: 1.7.2
Summary: A module for text based games
Home-page: https://github.com/menitoon/Oz-Engine-Rebooted
Author: SplatCraft
Author-email: splatcraft.5972@gmail.com
License: GNU General Public License v3 (GPLv3)
Classifier: Programming Language :: Python :: 3
Classifier: License :: OSI Approved :: GNU General Public License v3 (GPLv3)
Classifier: Operating System :: OS Independent
Requires-Python: >=3.2
